xaiev/ATSDS.py
xaiev/PRISM_pipeline.py
xaiev/Xrai_pipeline.py
xaiev/__init__.py
xaiev/cli.py
xaiev/core.py
xaiev/eval_ds_creation.py
xaiev/evaluation.py
xaiev/gradcam.py
xaiev/gradcamheatmap.py
xaiev/inference.py
xaiev/int_g_pipeline.py
xaiev/integrated_gradients.py
xaiev/lime_pipeline.py
xaiev/model.py
xaiev/release.py
xaiev/utilmethods.py
xaiev/utils.py
xaiev/visualization.py
xaiev-0.1.0.dist-info/METADATA
xaiev-0.1.0.dist-info/WHEEL
xaiev-0.1.0.dist-info/entry_points.txt
xaiev-0.1.0.dist-info/top_level.txt
xaiev-0.1.0.dist-info/RECORD
