Metadata-Version: 2.2
Name: xaiev
Version: 0.1.0
Summary: Add your description here
Author-email: Carsten Knoll <carsten.knoll@posteo.de>
Requires-Python: >=3.10
Requires-Dist: torch
Requires-Dist: torchvision
Requires-Dist: tabulate
Requires-Dist: urllib3
Requires-Dist: python-dotenv
Requires-Dist: opencv-python
Requires-Dist: ipydex
Requires-Dist: matplotlib
Requires-Dist: numpy
Requires-Dist: Pillow
Requires-Dist: tabulate
Requires-Dist: torchprism
Requires-Dist: scikit-image
Requires-Dist: icecream
Requires-Dist: lime
Requires-Dist: saliency
Requires-Dist: captum
